{
 "SoundBanksInfo": {
  "Platform": "Windows",
  "BasePlatform": "Windows",
  "SchemaVersion": "16",
  "SoundBankVersion": "154",
  "SoundBanks": [
   {
    "Id": "431205792",
    "Type": "Event",
    "GUID": "{15049214-A98A-4303-80C6-5C6418885C4C}",
    "Language": "SFX",
    "Hash": "{4C9A05E3-C505-16AF-17B8-F6A94C435F66}",
    "ObjectPath": "Play_New_Sound_SFX",
    "ShortName": "Play_New_Sound_SFX",
    "Path": "Event/Play_New_Sound_SFX.bnk",
    "Media": [
     {
      "Id": "933539871",
      "Language": "SFX",
      "Streaming": "true",
      "Location": "Loose",
      "ShortName": "Ambince.wav",
      "Path": "Media/933539871.wem",
      "CachePath": "1E/{1E36AB3F-C091-02AA-C56F-C6D4156C4440}.wem"
     }
    ],
    "Events": [
     {
      "Id": "431205792",
      "Name": "Play_New_Sound_SFX",
      "ObjectPath": "\\Events\\Default Work Unit\\Play_New_Sound_SFX",
      "GUID": "{15049214-A98A-4303-80C6-5C6418885C4C}",
      "DurationType": "Infinite",
      "MediaRefs": [
       {
        "Id": "933539871"
       }
      ]
     }
    ]
   }
  ],
  "FileHash": "{69991D27-C64C-5E89-9D3B-92A7B1504735}"
 }
}